{
  "type": "salvation:exteritio",
  "generator": {
    "type": "minecraft:noise",
    "settings": "salvation:exteritio_noise_settings",
    "biome_source": {
      "type": "minecraft:multi_noise",
      "biomes": [
        {
          "biome": "salvation:corrupted_mushroom_fields",
          "parameters": {
            "temperature": [
              -1.0,
              1.0
            ],
            "humidity": [
              -1.0,
              1.0
            ],
            "continentalness": [
              -1.2,
              -1.05
            ],
            "erosion": [
              -1.0,
              1.0
            ],
            "weirdness": [
              -1.0,
              1.0
            ],
            "depth": [
              0.0,
              0.0
            ],
            "offset": 0.0
          }
        },
        {
          "biome": "salvation:corrupted_deep_frozen_ocean",
          "parameters": {
            "temperature": [
              -1.0,
              -0.45
            ],
            "humidity": [
              -1.0,
              1.0
            ],
            "continentalness": [
              -1.05,
              -0.455
            ],
            "erosion": [
              -1.0,
              1.0
            ],
            "weirdness": [
              -1.0,
              1.0
            ],
            "depth": [
              0.0,
              0.0
            ],
            "offset": 0.0
          }
        },
        {
          "biome": "salvation:corrupted_deep_cold_ocean",
          "parameters": {
            "temperature": [
              -0.7,
              -0.15
            ],
            "humidity": [
              -1.0,
              1.0
            ],
            "continentalness": [
              -1.05,
              -0.455
            ],
            "erosion": [
              -1.0,
              1.0
            ],
            "weirdness": [
              -1.0,
              1.0
            ],
            "depth": [
              0.0,
              0.0
            ],
            "offset": 0.0
          }
        },
        {
          "biome": "salvation:corrupted_deep_ocean",
          "parameters": {
            "temperature": [
              -0.1,
              0.5
            ],
            "humidity": [
              -1.0,
              1.0
            ],
            "continentalness": [
              -1.05,
              -0.455
            ],
            "erosion": [
              -1.0,
              1.0
            ],
            "weirdness": [
              -1.0,
              1.0
            ],
            "depth": [
              0.0,
              0.0
            ],
            "offset": 0.0
          }
        },
        {
          "biome": "salvation:corrupted_deep_lukewarm_ocean",
          "parameters": {
            "temperature": [
              0.2,
              0.7
            ],
            "humidity": [
              -0.5,
              1.0
            ],
            "continentalness": [
              -1.05,
              -0.455
            ],
            "erosion": [
              -1.0,
              1.0
            ],
            "weirdness": [
              -1.0,
              1.0
            ],
            "depth": [
              0.0,
              0.0
            ],
            "offset": 0.0
          }
        },
        {
          "biome": "salvation:corrupted_frozen_ocean",
          "parameters": {
            "temperature": [
              -1.0,
              -0.45
            ],
            "humidity": [
              -1.0,
              1.0
            ],
            "continentalness": [
              -0.455,
              -0.19
            ],
            "erosion": [
              -1.0,
              1.0
            ],
            "weirdness": [
              -1.0,
              1.0
            ],
            "depth": [
              0.0,
              0.0
            ],
            "offset": 0.0
          }
        },
        {
          "biome": "salvation:corrupted_cold_ocean",
          "parameters": {
            "temperature": [
              -0.7,
              -0.15
            ],
            "humidity": [
              -1.0,
              1.0
            ],
            "continentalness": [
              -0.455,
              -0.19
            ],
            "erosion": [
              -1.0,
              1.0
            ],
            "weirdness": [
              -1.0,
              1.0
            ],
            "depth": [
              0.0,
              0.0
            ],
            "offset": 0.0
          }
        },
        {
          "biome": "salvation:corrupted_ocean",
          "parameters": {
            "temperature": [
              -0.1,
              0.5
            ],
            "humidity": [
              -1.0,
              1.0
            ],
            "continentalness": [
              -0.455,
              -0.19
            ],
            "erosion": [
              -1.0,
              1.0
            ],
            "weirdness": [
              -1.0,
              1.0
            ],
            "depth": [
              0.0,
              0.0
            ],
            "offset": 0.0
          }
        },
        {
          "biome": "salvation:corrupted_lukewarm_ocean",
          "parameters": {
            "temperature": [
              0.2,
              0.7
            ],
            "humidity": [
              -0.5,
              1.0
            ],
            "continentalness": [
              -0.455,
              -0.19
            ],
            "erosion": [
              -1.0,
              1.0
            ],
            "weirdness": [
              -1.0,
              1.0
            ],
            "depth": [
              0.0,
              0.0
            ],
            "offset": 0.0
          }
        },
        {
          "biome": "salvation:corrupted_warm_ocean",
          "parameters": {
            "temperature": [
              0.55,
              1.0
            ],
            "humidity": [
              0.2,
              1.0
            ],
            "continentalness": [
              -0.455,
              -0.19
            ],
            "erosion": [
              -1.0,
              1.0
            ],
            "weirdness": [
              -1.0,
              1.0
            ],
            "depth": [
              0.0,
              0.0
            ],
            "offset": 0.0
          }
        },
        {
          "biome": "salvation:corrupted_snowy_beach",
          "parameters": {
            "temperature": [
              -1.0,
              -0.35
            ],
            "humidity": [
              -1.0,
              1.0
            ],
            "continentalness": [
              -0.19,
              -0.11
            ],
            "erosion": [
              -1.0,
              1.0
            ],
            "weirdness": [
              -1.0,
              1.0
            ],
            "depth": [
              0.0,
              0.0
            ],
            "offset": 0.0
          }
        },
        {
          "biome": "salvation:corrupted_stony_shore",
          "parameters": {
            "temperature": [
              -0.2,
              0.6
            ],
            "humidity": [
              -1.0,
              0.5
            ],
            "continentalness": [
              -0.19,
              -0.11
            ],
            "erosion": [
              -1.0,
              1.0
            ],
            "weirdness": [
              -1.0,
              1.0
            ],
            "depth": [
              0.0,
              0.0
            ],
            "offset": 0.0
          }
        },
        {
          "biome": "salvation:corrupted_beach",
          "parameters": {
            "temperature": [
              0.2,
              1.0
            ],
            "humidity": [
              -1.0,
              1.0
            ],
            "continentalness": [
              -0.19,
              -0.11
            ],
            "erosion": [
              -1.0,
              1.0
            ],
            "weirdness": [
              -1.0,
              1.0
            ],
            "depth": [
              0.0,
              0.0
            ],
            "offset": 0.0
          }
        },
        {
          "biome": "salvation:corrupted_river",
          "parameters": {
            "temperature": [
              -1.0,
              1.0
            ],
            "humidity": [
              -1.0,
              1.0
            ],
            "continentalness": [
              -0.11,
              0.03
            ],
            "erosion": [
              -1.0,
              1.0
            ],
            "weirdness": [
              -1.0,
              1.0
            ],
            "depth": [
              0.0,
              0.0
            ],
            "offset": 0.0
          }
        },
        {
          "biome": "salvation:corrupted_swamp",
          "parameters": {
            "temperature": [
              0.5,
              1.0
            ],
            "humidity": [
              0.5,
              1.0
            ],
            "continentalness": [
              -0.11,
              0.03
            ],
            "erosion": [
              -1.0,
              1.0
            ],
            "weirdness": [
              -1.0,
              1.0
            ],
            "depth": [
              0.0,
              0.0
            ],
            "offset": 0.0
          }
        },
        {
          "biome": "salvation:corrupted_mangrove_swamp",
          "parameters": {
            "temperature": [
              0.7,
              1.0
            ],
            "humidity": [
              0.7,
              1.0
            ],
            "continentalness": [
              -0.11,
              0.03
            ],
            "erosion": [
              -1.0,
              1.0
            ],
            "weirdness": [
              -1.0,
              1.0
            ],
            "depth": [
              0.0,
              0.0
            ],
            "offset": 0.0
          }
        },
        {
          "biome": "salvation:corrupted_snowy_plains",
          "parameters": {
            "temperature": [
              -1.0,
              -0.35
            ],
            "humidity": [
              -0.4,
              0.8
            ],
            "continentalness": [
              0.03,
              0.55
            ],
            "erosion": [
              -1.0,
              1.0
            ],
            "weirdness": [
              -1.0,
              1.0
            ],
            "depth": [
              0.0,
              0.0
            ],
            "offset": 0.0
          }
        },
        {
          "biome": "salvation:corrupted_taiga",
          "parameters": {
            "temperature": [
              -0.5,
              0.2
            ],
            "humidity": [
              -0.2,
              1.0
            ],
            "continentalness": [
              0.03,
              0.55
            ],
            "erosion": [
              -1.0,
              1.0
            ],
            "weirdness": [
              -1.0,
              1.0
            ],
            "depth": [
              0.0,
              0.0
            ],
            "offset": 0.0
          }
        },
        {
          "biome": "salvation:corrupted_plains",
          "parameters": {
            "temperature": [
              0.1,
              0.8
            ],
            "humidity": [
              -0.3,
              0.4
            ],
            "continentalness": [
              0.03,
              0.55
            ],
            "erosion": [
              -1.0,
              1.0
            ],
            "weirdness": [
              -1.0,
              1.0
            ],
            "depth": [
              0.0,
              0.0
            ],
            "offset": 0.0
          }
        },
        {
          "biome": "salvation:corrupted_forest",
          "parameters": {
            "temperature": [
              0.2,
              0.8
            ],
            "humidity": [
              0.2,
              0.8
            ],
            "continentalness": [
              0.03,
              0.55
            ],
            "erosion": [
              -1.0,
              1.0
            ],
            "weirdness": [
              -1.0,
              1.0
            ],
            "depth": [
              0.0,
              0.0
            ],
            "offset": 0.0
          }
        },
        {
          "biome": "salvation:corrupted_birch_forest",
          "parameters": {
            "temperature": [
              0.2,
              0.8
            ],
            "humidity": [
              0.35,
              1.0
            ],
            "continentalness": [
              0.03,
              0.55
            ],
            "erosion": [
              -1.0,
              1.0
            ],
            "weirdness": [
              -1.0,
              1.0
            ],
            "depth": [
              0.0,
              0.0
            ],
            "offset": 0.0
          }
        },
        {
          "biome": "salvation:corrupted_flower_forest",
          "parameters": {
            "temperature": [
              0.3,
              0.8
            ],
            "humidity": [
              0.4,
              1.0
            ],
            "continentalness": [
              0.03,
              0.55
            ],
            "erosion": [
              -1.0,
              1.0
            ],
            "weirdness": [
              -1.0,
              1.0
            ],
            "depth": [
              0.0,
              0.0
            ],
            "offset": 0.0
          }
        },
        {
          "biome": "salvation:corrupted_savanna",
          "parameters": {
            "temperature": [
              0.55,
              1.0
            ],
            "humidity": [
              -0.4,
              0.3
            ],
            "continentalness": [
              0.03,
              0.55
            ],
            "erosion": [
              -1.0,
              1.0
            ],
            "weirdness": [
              -1.0,
              1.0
            ],
            "depth": [
              0.0,
              0.0
            ],
            "offset": 0.0
          }
        },
        {
          "biome": "salvation:corrupted_desert",
          "parameters": {
            "temperature": [
              0.7,
              1.0
            ],
            "humidity": [
              -1.0,
              0.1
            ],
            "continentalness": [
              0.03,
              0.55
            ],
            "erosion": [
              -1.0,
              1.0
            ],
            "weirdness": [
              -1.0,
              1.0
            ],
            "depth": [
              0.0,
              0.0
            ],
            "offset": 0.0
          }
        },
        {
          "biome": "salvation:corrupted_sparse_jungle",
          "parameters": {
            "temperature": [
              0.7,
              1.0
            ],
            "humidity": [
              0.4,
              0.9
            ],
            "continentalness": [
              0.03,
              0.55
            ],
            "erosion": [
              -1.0,
              1.0
            ],
            "weirdness": [
              -1.0,
              1.0
            ],
            "depth": [
              0.0,
              0.0
            ],
            "offset": 0.0
          }
        },
        {
          "biome": "salvation:corrupted_jungle",
          "parameters": {
            "temperature": [
              0.8,
              1.0
            ],
            "humidity": [
              0.7,
              1.0
            ],
            "continentalness": [
              0.03,
              0.55
            ],
            "erosion": [
              -1.0,
              1.0
            ],
            "weirdness": [
              -1.0,
              1.0
            ],
            "depth": [
              0.0,
              0.0
            ],
            "offset": 0.0
          }
        },
        {
          "biome": "salvation:corrupted_grove",
          "parameters": {
            "temperature": [
              -0.6,
              0.2
            ],
            "humidity": [
              -0.2,
              1.0
            ],
            "continentalness": [
              0.55,
              1.0
            ],
            "erosion": [
              -1.0,
              1.0
            ],
            "weirdness": [
              -1.0,
              1.0
            ],
            "depth": [
              0.0,
              0.0
            ],
            "offset": 0.0
          }
        },
        {
          "biome": "salvation:corrupted_meadow",
          "parameters": {
            "temperature": [
              0.1,
              0.7
            ],
            "humidity": [
              0.2,
              1.0
            ],
            "continentalness": [
              0.55,
              1.0
            ],
            "erosion": [
              -1.0,
              1.0
            ],
            "weirdness": [
              -1.0,
              1.0
            ],
            "depth": [
              0.0,
              0.0
            ],
            "offset": 0.0
          }
        },
        {
          "biome": "salvation:corrupted_windswept_forest",
          "parameters": {
            "temperature": [
              0.1,
              0.7
            ],
            "humidity": [
              0.0,
              0.8
            ],
            "continentalness": [
              0.55,
              1.0
            ],
            "erosion": [
              -1.0,
              1.0
            ],
            "weirdness": [
              -1.0,
              1.0
            ],
            "depth": [
              0.0,
              0.0
            ],
            "offset": 0.0
          }
        },
        {
          "biome": "salvation:corrupted_windswept_hills",
          "parameters": {
            "temperature": [
              -0.4,
              0.4
            ],
            "humidity": [
              -0.5,
              0.5
            ],
            "continentalness": [
              0.55,
              1.0
            ],
            "erosion": [
              -1.0,
              1.0
            ],
            "weirdness": [
              -1.0,
              1.0
            ],
            "depth": [
              0.0,
              0.0
            ],
            "offset": 0.0
          }
        },
        {
          "biome": "salvation:corrupted_frozen_peaks",
          "parameters": {
            "temperature": [
              -1.0,
              -0.45
            ],
            "humidity": [
              -1.0,
              1.0
            ],
            "continentalness": [
              0.55,
              1.0
            ],
            "erosion": [
              -1.0,
              1.0
            ],
            "weirdness": [
              -1.0,
              1.0
            ],
            "depth": [
              0.0,
              0.0
            ],
            "offset": 0.0
          }
        },
        {
          "biome": "salvation:corrupted_jagged_peaks",
          "parameters": {
            "temperature": [
              -0.8,
              -0.2
            ],
            "humidity": [
              -0.5,
              0.5
            ],
            "continentalness": [
              0.55,
              1.0
            ],
            "erosion": [
              -1.0,
              1.0
            ],
            "weirdness": [
              -1.0,
              1.0
            ],
            "depth": [
              0.0,
              0.0
            ],
            "offset": 0.0
          }
        },
        {
          "biome": "salvation:corrupted_lush_caves",
          "parameters": {
            "temperature": [
              0.6,
              1.0
            ],
            "humidity": [
              0.6,
              1.0
            ],
            "continentalness": [
              -1.0,
              1.0
            ],
            "erosion": [
              -1.0,
              1.0
            ],
            "weirdness": [
              -1.0,
              1.0
            ],
            "depth": [
              1.1,
              1.1
            ],
            "offset": 0.0
          }
        },
        {
          "biome": "salvation:corrupted_dripstone_caves",
          "parameters": {
            "temperature": [
              0.2,
              1.0
            ],
            "humidity": [
              -1.0,
              0.4
            ],
            "continentalness": [
              -1.0,
              1.0
            ],
            "erosion": [
              -1.0,
              1.0
            ],
            "weirdness": [
              -1.0,
              1.0
            ],
            "depth": [
              1.1,
              1.1
            ],
            "offset": 0.0
          }
        },
        {
          "biome": "salvation:corrupted_deep_dark",
          "parameters": {
            "temperature": [
              -1.0,
              1.0
            ],
            "humidity": [
              -0.8,
              0.1
            ],
            "continentalness": [
              -1.0,
              1.0
            ],
            "erosion": [
              -1.0,
              -0.4
            ],
            "weirdness": [
              -0.5,
              0.5
            ],
            "depth": [
              1.1,
              1.1
            ],
            "offset": 0.0
          }
        }
      ]
    }
  }
}
